nbexamples/__init__.py
nbexamples/_version.py
nbexamples/handlers.py
nbexamples/strip_output.py
nbexamples/static/examples.css
nbexamples/static/examples.js
nbexamples/static/main.js
nbexamples/static/submit-example-button.js
nbexamples-0.3.1.dist-info/DESCRIPTION.rst
nbexamples-0.3.1.dist-info/METADATA
nbexamples-0.3.1.dist-info/RECORD
nbexamples-0.3.1.dist-info/WHEEL
nbexamples-0.3.1.dist-info/metadata.json
nbexamples-0.3.1.dist-info/top_level.txt
