Metadata-Version: 2.0
Name: nbexamples
Version: 0.3.1
Summary: UNKNOWN
Home-page: UNKNOWN
Author: UNKNOWN
Author-email: UNKNOWN
License: BSD
Platform: Jupyter Notebook
Requires-Dist: nbconvert
Requires-Dist: nbformat
Requires-Dist: notebook (>=4.2.0)
